dmp_af/__init__.py
dmp_af/dags.py
dmp_af/py.typed
dmp_af/builder/__init__.py
dmp_af/builder/backfill_dag_components.py
dmp_af/builder/dag_components.py
dmp_af/builder/dbt_model_path_graph_builder.py
dmp_af/builder/dmp_af_builder.py
dmp_af/builder/domain_dag.py
dmp_af/builder/maintenance_dag_components.py
dmp_af/builder/task_dependencies.py
dmp_af/common/__init__.py
dmp_af/common/af_callbacks.py
dmp_af/common/af_scheduling_utils.py
dmp_af/common/constants.py
dmp_af/common/cron.py
dmp_af/common/scheduling.py
dmp_af/common/utils.py
dmp_af/conf/__init__.py
dmp_af/conf/config.py
dmp_af/integrations/__init__.py
dmp_af/integrations/af_callbacks/__init__.py
dmp_af/integrations/af_callbacks/callbacks.py
dmp_af/integrations/mcd/__init__.py
dmp_af/integrations/mcd/callbacks.py
dmp_af/integrations/mcd/dbt_core.py
dmp_af/integrations/tableau/__init__.py
dmp_af/integrations/tableau/auth.py
dmp_af/integrations/tableau/exceptions.py
dmp_af/integrations/tableau/extracts.py
dmp_af/operators/__init__.py
dmp_af/operators/base.py
dmp_af/operators/branch.py
dmp_af/operators/kubernetes_pod.py
dmp_af/operators/macros.py
dmp_af/operators/run.py
dmp_af/operators/sensors.py
dmp_af/operators/supplemental.py
dmp_af/operators/venv.py
dmp_af/parser/__init__.py
dmp_af/parser/dbt_node_model.py
dmp_af/parser/dbt_profiles.py
dmp_af/parser/dbt_source_model.py
dmp_af-0.16.0.dist-info/METADATA
dmp_af-0.16.0.dist-info/WHEEL
dmp_af-0.16.0.dist-info/entry_points.txt
dmp_af-0.16.0.dist-info/licenses/AUTHORS
dmp_af-0.16.0.dist-info/licenses/LICENSE
dmp_af-0.16.0.dist-info/licenses/NOTICE
dmp_af-0.16.0.dist-info/RECORD
