Metadata-Version: 2.4
Name: dmp-af
Version: 0.16.0
Summary: Distibuted dbt runs on Apache Airflow
Project-URL: Homepage, https://github.com/dmp-labs/dmp-af
Project-URL: Documentation, https://dmp-labs.github.io/dmp-af/
Project-URL: Release Notes, https://github.com/dmp-labs/dmp-af/blob/main/CHANGELOG.md
Project-URL: Source Code, https://github.com/dmp-labs/dmp-af
Author-email: Nikita Yurasov <nikitayurasov@ijkos.com>, Evgeny Ermakov <jk.ermakov@ijkos.com>, Leonid Kozhinov <lkozhinov@ijkos.com>
License-Expression: Apache-2.0
License-File: AUTHORS
License-File: LICENSE
License-File: NOTICE
Keywords: airflow,dbt,python
Classifier: License :: OSI Approved :: Apache Software License
Classifier: Programming Language :: Python :: 3.10
Classifier: Programming Language :: Python :: 3.11
Classifier: Programming Language :: Python :: 3.12
Requires-Python: <3.14,>=3.10
Requires-Dist: apache-airflow[cncf-kubernetes,fab]<3.2.0,>=2.6
Requires-Dist: attrs>=23.1
Requires-Dist: cachetools<7,>=5.3
Requires-Dist: croniter>=3.0
Requires-Dist: dbt-core<2,>=1.7
Requires-Dist: packaging>=21.0
Requires-Dist: pydantic<3.0.0,>=1.10
Requires-Dist: pytest-env>=1.0.0
Requires-Dist: pytest>=7.4.0
Requires-Dist: typer>=0.9
Requires-Dist: virtualenv>=20.27.0
Provides-Extra: all
Requires-Dist: airflow-mcd<0.4.0,>=0.3.3; extra == 'all'
Requires-Dist: pycarlo>=0.9; extra == 'all'
Requires-Dist: setuptools; extra == 'all'
Requires-Dist: tableauserverclient<0.26.0,>=0.25.0; extra == 'all'
Provides-Extra: mcd
Requires-Dist: airflow-mcd<0.4.0,>=0.3.3; extra == 'mcd'
Requires-Dist: pycarlo>=0.9; extra == 'mcd'
Requires-Dist: setuptools; extra == 'mcd'
Provides-Extra: tableau
Requires-Dist: tableauserverclient<0.26.0,>=0.25.0; extra == 'tableau'
